spot_connect/__init__.py
spot_connect/bash_scripts.py
spot_connect/connect.py
spot_connect/ec2_methods.py
spot_connect/efs_methods.py
spot_connect/fleet_methods.py
spot_connect/iam_methods.py
spot_connect/instance_manager.py
spot_connect/instance_methods.py
spot_connect/interactive.py
spot_connect/keras_callback.py
spot_connect/s3_methods.py
spot_connect/spotted.py
spot_connect/sutils.py
spot_connect/data/ami_data.csv
spot_connect/data/key_pair_default_dir.txt
spot_connect/data/profiles.txt
spot_connect/data/spot_instance_pricing.csv
spot_connect-1.0.7.dist-info/LICENSE.txt
spot_connect-1.0.7.dist-info/METADATA
spot_connect-1.0.7.dist-info/WHEEL
spot_connect-1.0.7.dist-info/entry_points.txt
spot_connect-1.0.7.dist-info/top_level.txt
spot_connect-1.0.7.dist-info/RECORD
