Metadata-Version: 2.1
Name: spot-connect
Version: 1.0.7
Summary: A package to create and manage AWS resources, centered around EC2 spot-instances
Home-page: https://github.com/losDaniel/spot-connect.git
Author: Carlos Valcarcel
Author-email: carlos.d.valcarcel.w@gmail.com
License: MIT
Keywords: aws ec2 cloud ssh machinelearning virtualmachine
Platform: UNKNOWN
Requires-Python: >=3.0
Requires-Dist: boto3
Requires-Dist: netaddr
Requires-Dist: paramiko
Requires-Dist: path
